qstrader/__init__.py
qstrader/settings.py
qstrader/alpha_model/__init__.py
qstrader/alpha_model/alpha_model.py
qstrader/alpha_model/fixed_signals.py
qstrader/alpha_model/single_signal.py
qstrader/asset/__init__.py
qstrader/asset/asset.py
qstrader/asset/cash.py
qstrader/asset/equity.py
qstrader/asset/universe/__init__.py
qstrader/asset/universe/dynamic.py
qstrader/asset/universe/static.py
qstrader/asset/universe/universe.py
qstrader/broker/__init__.py
qstrader/broker/broker.py
qstrader/broker/simulated_broker.py
qstrader/broker/fee_model/__init__.py
qstrader/broker/fee_model/fee_model.py
qstrader/broker/fee_model/percent_fee_model.py
qstrader/broker/fee_model/zero_fee_model.py
qstrader/broker/portfolio/__init__.py
qstrader/broker/portfolio/portfolio.py
qstrader/broker/portfolio/portfolio_event.py
qstrader/broker/portfolio/position.py
qstrader/broker/portfolio/position_handler.py
qstrader/broker/transaction/__init__.py
qstrader/broker/transaction/transaction.py
qstrader/data/__init__.py
qstrader/data/backtest_data_handler.py
qstrader/data/daily_bar_csv.py
qstrader/exchange/__init__.py
qstrader/exchange/exchange.py
qstrader/exchange/simulated_exchange.py
qstrader/execution/__init__.py
qstrader/execution/execution_handler.py
qstrader/execution/order.py
qstrader/execution/execution_algo/__init__.py
qstrader/execution/execution_algo/execution_algo.py
qstrader/execution/execution_algo/market_order.py
qstrader/portcon/__init__.py
qstrader/portcon/pcm.py
qstrader/portcon/optimiser/__init__.py
qstrader/portcon/optimiser/equal_weight.py
qstrader/portcon/optimiser/fixed_weight.py
qstrader/portcon/optimiser/optimiser.py
qstrader/portcon/order_sizer/__init__.py
qstrader/portcon/order_sizer/dollar_weighted.py
qstrader/portcon/order_sizer/long_short.py
qstrader/portcon/order_sizer/order_sizer.py
qstrader/risk_model/__init__.py
qstrader/risk_model/risk_model.py
qstrader/signals/__init__.py
qstrader/signals/buffer.py
qstrader/signals/momentum.py
qstrader/signals/signal.py
qstrader-0.3.0.dist-info/METADATA
qstrader-0.3.0.dist-info/WHEEL
qstrader-0.3.0.dist-info/licenses/LICENSE
qstrader-0.3.0.dist-info/RECORD
