Metadata-Version: 2.3
Name: qstrader
Version: 0.3.0
Summary: QSTrader backtesting simulation engine
Project-URL: Homepage, https://github.com/mhallsmoore/qstrader
Project-URL: Issues, https://github.com/mhallsmoore/qstrader/issues
Project-URL: Documentation, https://www.quantstart.com/qstrader/
Project-URL: Website, https://www.quantstart.com
Author-email: Michael Halls-Moore <support@quantstart.com>
Maintainer-email: Juliette James <juliette.james@quantstart.com>
License-File: LICENSE
Keywords: algorithmic trading,backtesting,systematic trading
Classifier: Development Status :: 5 - Production/Stable
Classifier: License :: OSI Approved :: MIT License
Classifier: Operating System :: OS Independent
Classifier: Programming Language :: Python :: 3
Classifier: Programming Language :: Python :: 3.9
Classifier: Programming Language :: Python :: 3.10
Classifier: Programming Language :: Python :: 3.11
Classifier: Programming Language :: Python :: 3.12
Requires-Python: >=3.9
Requires-Dist: click>=8.1
Requires-Dist: matplotlib>=3.8
Requires-Dist: numpy>=2.0.0
Requires-Dist: pandas>=2.2
Requires-Dist: seaborn>=0.13
